<?xml version="1.0" encoding="UTF-8"?>
<!--This file was created by G+Smo 21.12.0-->
<xml>
 <Matrix rows="5" cols="7" id="0">0.25 187 0.07200433210835407 1.494069956130974 38.44198542521845 19.11488002754307 640 
0.125 551 0.00223794584772749 0.08891133150391392 6.392290961063838 19.66312869451263 1280 
0.0625 1855 9.218281418152753e-05 0.008307064125007171 1.418184002487905 19.68123803859379 2560 
0.03125 6767 5.023827040968006e-06 0.0009645869713267974 0.3431914123460694 19.68187248993015 5120 
0.015625 25807 3.007403281987151e-07 0.0001182760768874801 0.08502872295394978 19.68190391260518 10240 
</Matrix>
 <string label="Degree" id="1">3</string>
 <string label="Regularity" id="2">2</string>
 <string label="NumRefine" id="3">4</string>
 <string label="Method" id="4">1</string>
</xml>

