<?xml version="1.0" encoding="UTF-8"?>
<!--This file was created by G+Smo 21.12.0-->
<xml>
 <Matrix rows="5" cols="8" id="0">0.25 55 0.8571992367934497 9.18205713243486 118.987879832921 0.3296827994075155 nan 102787.2 
0.125 171 0.230315211900228 3.532173789202913 62.14252651917897 0.03559295759684336 nan 205574.4 
0.0625 595 0.04970749405025699 0.944996477362698 19.5413945413414 0.02861105110055944 nan 411148.8 
0.03125 2211 0.001992118033195897 0.04552954659330429 1.622198055362214 0.004717079712778159 nan 822297.6 
0.015625 8515 6.07271489482096e-05 0.001831944901569552 0.2531226408187316 0.000584818935193701 nan 1644595.2 
</Matrix>
 <string label="Label" id="1">Meshsize, dofs, l2err, h1err, h2err, iFaceErr, cond_num, (penalty)</string>
 <string label="Degree" id="2">3</string>
 <string label="Regularity" id="3">2</string>
 <string label="NumRefine" id="4">4</string>
 <string label="Method" id="5">1</string>
</xml>

