<?xml version="1.0" encoding="UTF-8"?>
<!--This file was created by G+Smo 21.12.0-->
<xml>
 <Matrix rows="5" cols="8" id="0">0.25 55 0.3978542000029348 9.46603309745013 271.2038881603269 50.51743285337009 nan 0.71452 
0.125 171 0.01680906791058741 0.4799184425392339 23.6779889520018 1.658303334861442 -nan 1.42904 
0.0625 595 0.000621492480301751 0.0319755657563537 4.186707102104552 0.1061775712185281 nan 2.85808 
0.03125 2211 3.049430890010706e-05 0.003214332402611117 0.9471004712651406 0.01240254002679318 -nan 5.71616 
0.015625 8515 1.774114146728547e-06 0.0003760639243812688 0.2295244680006326 0.001527805301767266 -nan 11.43232 
</Matrix>
 <string label="Label" id="1">Meshsize, dofs, l2err, h1err, h2err, iFaceErr, cond_num, (penalty)</string>
 <string label="Degree" id="2">3</string>
 <string label="Regularity" id="3">2</string>
 <string label="NumRefine" id="4">4</string>
 <string label="Method" id="5">1</string>
</xml>

