<?xml version="1.0" encoding="UTF-8"?>
<!--This file was created by G+Smo 21.12.0-->
<xml>
 <Matrix rows="5" cols="8" id="0">0.25 55 6.477906356249177 42.71067664110931 303.1986125031186 0.3004981892482339 nan 1608444 
0.125 171 0.4861751625450401 5.578175381279199 74.98073087715127 0.01213597712005714 -nan 3216888 
0.0625 595 0.162496418989049 2.731505772112689 50.56645432784281 0.007194988386987239 nan 6433776 
0.03125 2211 0.02193093499503793 0.4265887590863576 9.037230464839083 0.003816979833893512 -nan 12867552 
0.015625 8515 0.0008540202770004882 0.02003351551926038 0.708294631541408 0.000562007227849756 -nan 25735104 
</Matrix>
 <string label="Label" id="1">Meshsize, dofs, l2err, h1err, h2err, iFaceErr, cond_num, (penalty)</string>
 <string label="Degree" id="2">3</string>
 <string label="Regularity" id="3">2</string>
 <string label="NumRefine" id="4">4</string>
 <string label="Method" id="5">1</string>
</xml>

