<?xml version="1.0" encoding="UTF-8"?>
<!--This file was created by G+Smo 21.12.0-->
<xml>
 <Matrix rows="5" cols="8" id="0">0.25 78 0.2814142109675413 4.436578151842291 78.60205900237853 0.2558991153430751 nan 70640.8 
0.125 210 0.08930409629450985 1.698600223854502 35.4337593836899 0.04836675813977292 -nan 141281.6 
0.0625 666 0.002769629748693817 0.07107082939539582 2.117837014608514 0.008295901670949618 nan 282563.2 
0.03125 2346 1.37493914104885e-05 0.0005243893381484377 0.06264209269504302 0.0004279071800238597 -nan 565126.4 
0.015625 8778 9.030484468620453e-08 1.279519605740012e-05 0.006885905823064008 2.413227683296889e-05 -nan 1130252.8 
</Matrix>
 <string label="Label" id="1">Meshsize, dofs, l2err, h1err, h2err, iFaceErr, cond_num, (penalty)</string>
 <string label="Degree" id="2">4</string>
 <string label="Regularity" id="3">3</string>
 <string label="NumRefine" id="4">4</string>
 <string label="Method" id="5">1</string>
</xml>

