<?xml version="1.0" encoding="UTF-8"?>
<!--This file was created by G+Smo 21.12.0-->
<xml>
 <Matrix rows="5" cols="8" id="0">0.25 55 0.3274579781699632 6.681583318536709 166.1337444807542 27.02679054778201 nan 0.00444 
0.125 171 0.01691936125591909 0.5238957129034128 27.4953939470285 2.601555950052177 nan 0.008880000000000001 
0.0625 595 0.0006197633034586989 0.03186509952313296 4.176996439137065 0.1021257855437072 nan 0.01776 
0.03125 2211 3.044095599898623e-05 0.003206354477250533 0.9457417396406146 0.01184006861528023 nan 0.03552 
0.015625 8515 1.772503302131151e-06 0.0003755458184348797 0.2293507161719332 0.001456070042050531 nan 0.07104000000000001 
</Matrix>
 <string label="Label" id="1">Meshsize, dofs, l2err, h1err, h2err, iFaceErr, cond_num, (penalty)</string>
 <string label="Degree" id="2">3</string>
 <string label="Regularity" id="3">2</string>
 <string label="NumRefine" id="4">4</string>
 <string label="Method" id="5">1</string>
</xml>

