<?xml version="1.0" encoding="UTF-8"?>
<!--This file was created by G+Smo 21.12.0-->
<xml>
 <Matrix rows="5" cols="8" id="0">0.25 78 0.103257868357553 2.16884186649716 53.0435530170446 2.301442768976464 -nan 0.471 
0.125 210 0.00364098591737768 0.1406090840035707 7.474237058165225 0.37359064550323 nan 0.9419999999999999 
0.0625 666 3.637224785715e-05 0.00406595310026278 0.5510578497578275 0.01074776079677233 nan 1.884 
0.03125 2346 7.245226609546973e-07 0.0001975467685491197 0.05759738325577003 0.0004801778389199957 nan 3.768 
0.015625 8778 2.012020075796165e-08 1.153297743170998e-05 0.006863487442665685 2.709825692293504e-05 nan 7.536 
</Matrix>
 <string label="Label" id="1">Meshsize, dofs, l2err, h1err, h2err, iFaceErr, cond_num, (penalty)</string>
 <string label="Degree" id="2">4</string>
 <string label="Regularity" id="3">3</string>
 <string label="NumRefine" id="4">4</string>
 <string label="Method" id="5">1</string>
</xml>

