<?xml version="1.0" encoding="UTF-8"?>
<!--This file was created by G+Smo 21.12.0-->
<xml>
 <Matrix rows="5" cols="8" id="0">0.25 55 0.2405541833219754 4.888606984716856 148.7309308897125 18.82484398883067 -nan 20.8904 
0.125 171 0.01778539748387873 0.4958324975202328 26.79323032396805 1.982183884132875 -nan 41.7808 
0.0625 595 0.0006207324759229685 0.03488606626389132 5.246255323640065 0.2473082495893314 nan 83.5616 
0.03125 2211 3.006554872640939e-05 0.003282015190401165 1.011690140622365 0.02296998366995103 -nan 167.1232 
0.015625 8515 1.758259764428158e-06 0.0003799536336110163 0.2374748011964108 0.002773821110676021 -nan 334.2464 
</Matrix>
 <string label="Label" id="1">Meshsize, dofs, l2err, h1err, h2err, iFaceErr, cond_num, (penalty)</string>
 <string label="Degree" id="2">3</string>
 <string label="Regularity" id="3">2</string>
 <string label="NumRefine" id="4">4</string>
 <string label="Method" id="5">1</string>
</xml>

