<?xml version="1.0" encoding="UTF-8"?>
<!--This file was created by G+Smo 21.12.0-->
<xml>
 <Matrix rows="5" cols="8" id="0">0.25 55 0.4916927395209455 6.503480561852215 104.6719942524787 0.3838111434537005 -nan 10388.4 
0.125 171 0.1347503740800142 2.404462800188308 47.95180577572807 0.1294601687399807 nan 20776.8 
0.0625 595 0.009316894496367723 0.2024611507904298 6.296735922080585 0.04265662442668784 nan 41553.6 
0.03125 2211 0.0002483435289984966 0.007195852148132862 0.9714771916239545 0.004993935902764255 nan 83107.2 
0.015625 8515 7.650427437489035e-06 0.000456224791790003 0.2291208519396487 0.0005937016697395036 -nan 166214.4 
</Matrix>
 <string label="Label" id="1">Meshsize, dofs, l2err, h1err, h2err, iFaceErr, cond_num, (penalty)</string>
 <string label="Degree" id="2">3</string>
 <string label="Regularity" id="3">2</string>
 <string label="NumRefine" id="4">4</string>
 <string label="Method" id="5">1</string>
</xml>

