<?xml version="1.0" encoding="UTF-8"?>
<!--This file was created by G+Smo 21.12.0-->
<xml>
 <Matrix rows="5" cols="8" id="0">0.25 55 0.3275022022309975 6.683349816568754 166.2044685966436 27.04397944410359 nan 0.00544 
0.125 171 0.01691861797362239 0.5237457877759185 27.48312650023756 2.598893671748619 nan 0.01088 
0.0625 595 0.0006197655372773866 0.03186523864178996 4.177008615158594 0.1021309478642082 nan 0.02176 
0.03125 2211 3.044102730481698e-05 0.003206364884852537 0.9457434987727706 0.0118408127775887 nan 0.04352 
0.015625 8515 1.772505459920705e-06 0.0003755464927960515 0.2293509407514936 0.001456164914837968 nan 0.08704000000000001 
</Matrix>
 <string label="Label" id="1">Meshsize, dofs, l2err, h1err, h2err, iFaceErr, cond_num, (penalty)</string>
 <string label="Degree" id="2">3</string>
 <string label="Regularity" id="3">2</string>
 <string label="NumRefine" id="4">4</string>
 <string label="Method" id="5">1</string>
</xml>

