<?xml version="1.0" encoding="UTF-8"?>
<!--This file was created by G+Smo 21.12.0-->
<xml>
 <Matrix rows="5" cols="8" id="0">0.25 55 0.2491998139789173 4.538056666824593 101.6383850991828 6.119656405323031 nan 30.39688 
0.125 171 0.01851099690675378 0.4780830765983058 21.88653276312946 0.9176161300085109 -nan 60.79376 
0.0625 595 0.0006272312236353853 0.03095737706683517 4.149769374608558 0.08715103242686347 nan 121.58752 
0.03125 2211 3.023677176232886e-05 0.003128869313866453 0.9413996957575467 0.009635832167223564 -nan 243.17504 
0.015625 8515 1.763278266473667e-06 0.0003704202515906831 0.2287555036640564 0.001156955282143269 -nan 486.35008 
</Matrix>
 <string label="Label" id="1">Meshsize, dofs, l2err, h1err, h2err, iFaceErr, cond_num, (penalty)</string>
 <string label="Degree" id="2">3</string>
 <string label="Regularity" id="3">2</string>
 <string label="NumRefine" id="4">4</string>
 <string label="Method" id="5">1</string>
</xml>

