<?xml version="1.0" encoding="UTF-8"?>
<!--This file was created by G+Smo 21.12.0-->
<xml>
 <Matrix rows="5" cols="8" id="0">0.25 78 0.1083536122339513 2.219777901795789 54.6048937728084 2.10055041685678 nan 54.4756 
0.125 210 0.005003320665418468 0.1599497007416396 7.583622482260996 0.3354633046256972 -nan 108.9512 
0.0625 666 3.871933012731505e-05 0.004080058587094054 0.550268858779734 0.01011039545176632 nan 217.9024 
0.03125 2346 7.294301637658166e-07 0.0001973219283820987 0.05755346912250219 0.0004554256829046006 -nan 435.8048 
0.015625 8778 2.014047562864677e-08 1.152552636265941e-05 0.006860735708045703 2.560781141297163e-05 nan 871.6096 
</Matrix>
 <string label="Label" id="1">Meshsize, dofs, l2err, h1err, h2err, iFaceErr, cond_num, (penalty)</string>
 <string label="Degree" id="2">4</string>
 <string label="Regularity" id="3">3</string>
 <string label="NumRefine" id="4">4</string>
 <string label="Method" id="5">1</string>
</xml>

