<?xml version="1.0" encoding="UTF-8"?>
<!--This file was created by G+Smo 21.12.0-->
<xml>
 <Matrix rows="5" cols="8" id="0">0.25 55 0.2708848390652738 4.789303875292295 96.38004031040575 1.476258043945249 nan 97.6276 
0.125 171 0.02312146292328224 0.5492174196805158 21.77855873665521 0.5962601157741573 nan 195.2552 
0.0625 595 0.0007029609083987893 0.03171613329441212 4.091813494075882 0.05378349093857313 nan 390.5104 
0.03125 2211 3.163331581134604e-05 0.003130336322645037 0.9344801366758459 0.005390503768527197 nan 781.0208 
0.015625 8515 1.800011462098982e-06 0.0003701201834323942 0.2279307948258727 0.0006320334556720274 nan 1562.0416 
</Matrix>
 <string label="Label" id="1">Meshsize, dofs, l2err, h1err, h2err, iFaceErr, cond_num, (penalty)</string>
 <string label="Degree" id="2">3</string>
 <string label="Regularity" id="3">2</string>
 <string label="NumRefine" id="4">4</string>
 <string label="Method" id="5">1</string>
</xml>

