<?xml version="1.0" encoding="UTF-8"?>
<!--This file was created by G+Smo 21.12.0-->
<xml>
 <Matrix rows="5" cols="8" id="0">0.25 78 0.1059716344307918 2.213207263194082 53.85739037967645 2.602139253861761 -nan 11.65668 
0.125 210 0.003909758346837979 0.144648776421144 7.587163334979891 0.3967745364639927 nan 23.31336 
0.0625 666 3.713107800745695e-05 0.004096462576706805 0.5554883359225885 0.01201844322969037 nan 46.62672 
0.03125 2346 7.289591467544468e-07 0.0001984044588208762 0.05791329618116135 0.0005950172095851799 nan 93.25344 
0.015625 8778 2.01718702261273e-08 1.155974651906712e-05 0.006884113989256764 3.500586108722953e-05 nan 186.50688 
</Matrix>
 <string label="Label" id="1">Meshsize, dofs, l2err, h1err, h2err, iFaceErr, cond_num, (penalty)</string>
 <string label="Degree" id="2">4</string>
 <string label="Regularity" id="3">3</string>
 <string label="NumRefine" id="4">4</string>
 <string label="Method" id="5">1</string>
</xml>

