<?xml version="1.0" encoding="UTF-8"?>
<!--This file was created by G+Smo 21.12.0-->
<xml>
 <Matrix rows="5" cols="8" id="0">0.25 55 0.8232292382567641 9.211670203787821 144.4913110262785 0.08504071144859299 -nan 23906.08 
0.125 171 0.3936008538921423 4.308156682284784 76.49582033545878 0.1155600776044498 nan 47812.16 
0.0625 595 0.05111524325829302 1.034111712920398 24.87730407337359 0.05266897380523575 nan 95624.32000000001 
0.03125 2211 0.002117395311307438 0.04762870210949278 2.280987901267222 0.01057644112047307 -nan 191248.64 
0.015625 8515 5.340787268207759e-05 0.001613982587316286 0.4700032346121592 0.001191206122671795 0 382497.28 
</Matrix>
 <string label="Label" id="1">Meshsize, dofs, l2err, h1err, h2err, iFaceErr, cond_num, (penalty)</string>
 <string label="Degree" id="2">3</string>
 <string label="Regularity" id="3">2</string>
 <string label="NumRefine" id="4">4</string>
 <string label="Method" id="5">1</string>
</xml>

