<?xml version="1.0" encoding="UTF-8"?>
<!--This file was created by G+Smo 21.12.0-->
<xml>
 <Matrix rows="5" cols="8" id="0">0.25 55 2.942016115485267 104.1361243584225 3732.91697725149 565.8878111969132 nan 0.08531999999999999 
0.125 171 0.09743285031734222 2.078466166177255 55.56911163445848 1.506385224359292 -nan 0.17064 
0.0625 595 0.003184708455286482 0.1176359283299335 9.552551823454303 0.1496799663452701 nan 0.34128 
0.03125 2211 0.0001331447379307264 0.01004638448259922 1.982174112470982 0.01353261937731906 nan 0.6825599999999999 
0.015625 8515 7.326058049105433e-06 0.001123337921940108 0.4691406405233118 0.001558619310789799 0 1.36512 
</Matrix>
 <string label="Label" id="1">Meshsize, dofs, l2err, h1err, h2err, iFaceErr, cond_num, (penalty)</string>
 <string label="Degree" id="2">3</string>
 <string label="Regularity" id="3">2</string>
 <string label="NumRefine" id="4">4</string>
 <string label="Method" id="5">1</string>
</xml>

