<?xml version="1.0" encoding="UTF-8"?>
<!--This file was created by G+Smo 21.12.0-->
<xml>
 <Matrix rows="5" cols="8" id="0">0.25 55 0.4975299165898445 7.537883582984594 139.9505060893464 9.307167206940854 nan 12.66984 
0.125 171 0.09801477128297576 2.309351101759729 88.72725540274136 11.2494318431707 nan 25.33968 
0.0625 595 0.004836827560948904 0.3672048147856372 49.34469925775749 5.401107243250408 nan 50.67936 
0.03125 2211 0.0001404261779991565 0.01325880204617819 3.05214435486588 0.1885884529042362 -nan 101.35872 
0.015625 8515 8.016850409995697e-06 0.001680421750306702 0.8166097014271867 0.03819299314388937 0 202.71744 
</Matrix>
 <string label="Label" id="1">Meshsize, dofs, l2err, h1err, h2err, iFaceErr, cond_num, (penalty)</string>
 <string label="Degree" id="2">3</string>
 <string label="Regularity" id="3">2</string>
 <string label="NumRefine" id="4">4</string>
 <string label="Method" id="5">1</string>
</xml>

