<?xml version="1.0" encoding="UTF-8"?>
<!--This file was created by G+Smo 21.12.0-->
<xml>
 <Matrix rows="5" cols="8" id="0">0.25 55 21.24395425267403 421.7031525679339 10102.00093103248 2136.648044370608 nan 5.50568 
0.125 171 0.09853337616325016 2.100198217044838 56.50117004672382 2.148401658687782 -nan 11.01136 
0.0625 595 0.003213769247114688 0.1183281132521496 9.597229508014645 0.1885936402552816 nan 22.02272 
0.03125 2211 0.0001336034838732772 0.01007435400602015 1.987702123232085 0.01849834112513715 -nan 44.04544 
0.015625 8515 7.338350949716623e-06 0.001125015019327986 0.469840155299172 0.002177501604002075 0 88.09088 
</Matrix>
 <string label="Label" id="1">Meshsize, dofs, l2err, h1err, h2err, iFaceErr, cond_num, (penalty)</string>
 <string label="Degree" id="2">3</string>
 <string label="Regularity" id="3">2</string>
 <string label="NumRefine" id="4">4</string>
 <string label="Method" id="5">1</string>
</xml>

