<?xml version="1.0" encoding="UTF-8"?>
<!--This file was created by G+Smo 21.12.0-->
<xml>
 <Matrix rows="5" cols="8" id="0">0.25 55 0.2539107444000604 4.717409769643177 93.54844034704734 1.119497616983403 nan 0.00424 
0.125 171 0.03869454297624084 1.005105062971462 33.90679159334186 0.2595494950933078 nan 0.00848 
0.0625 595 0.001074516295573643 0.06079604457751832 5.59358408020895 0.02330798874890417 nan 0.01696 
0.03125 2211 5.071996112544995e-05 0.006046381728396986 1.229239305150594 0.002882474672637164 nan 0.03392 
0.015625 8515 2.940386055908086e-06 0.0007101385819800991 0.2969452670599628 0.0003633721313496468 0 0.06784 
</Matrix>
 <string label="Label" id="1">Meshsize, dofs, l2err, h1err, h2err, iFaceErr, cond_num, (penalty)</string>
 <string label="Degree" id="2">3</string>
 <string label="Regularity" id="3">2</string>
 <string label="NumRefine" id="4">4</string>
 <string label="Method" id="5">1</string>
</xml>

