<?xml version="1.0" encoding="UTF-8"?>
<!--This file was created by G+Smo 21.12.0-->
<xml>
 <Matrix rows="5" cols="8" id="0">0.25 55 0.5665449593750666 6.096693706686595 102.0264638105881 0.01903155599985493 nan 897500 
0.125 171 0.0885222354726596 1.771773823140561 48.22331253924871 0.007124152346588479 -nan 1795000 
0.0625 595 0.008384489723011989 0.2020439577773998 8.333367586204639 0.004256339315330347 nan 3590000 
0.03125 2211 7.592626390647327e-05 0.006233697723798645 1.231157408919805 0.0002299250265609523 -nan 7180000 
0.015625 8515 3.05202216747961e-06 0.0007103514267900533 0.2968434705971501 1.266300558787039e-05 0 14360000 
</Matrix>
 <string label="Label" id="1">Meshsize, dofs, l2err, h1err, h2err, iFaceErr, cond_num, (penalty)</string>
 <string label="Degree" id="2">3</string>
 <string label="Regularity" id="3">2</string>
 <string label="NumRefine" id="4">4</string>
 <string label="Method" id="5">1</string>
</xml>

