<?xml version="1.0" encoding="UTF-8"?>
<!--This file was created by G+Smo 21.12.0-->
<xml>
 <Matrix rows="5" cols="8" id="0">0.25 55 0.4937193528861634 5.779863916569214 100.6607570484344 0.02198697208754936 -nan 616812 
0.125 171 0.08499145592053732 1.740224049633649 47.60420551325125 0.008445003478178672 -nan 1233624 
0.0625 595 0.006419316922676971 0.1595348694230298 7.360870209624468 0.004540006537731402 nan 2467248 
0.03125 2211 6.712756324953038e-05 0.006157112345524434 1.230056699175375 0.0002303876008559233 nan 4934496 
0.015625 8515 3.015683641992702e-06 0.0007102000190865179 0.2968385393656599 1.266889108562284e-05 0 9868992 
</Matrix>
 <string label="Label" id="1">Meshsize, dofs, l2err, h1err, h2err, iFaceErr, cond_num, (penalty)</string>
 <string label="Degree" id="2">3</string>
 <string label="Regularity" id="3">2</string>
 <string label="NumRefine" id="4">4</string>
 <string label="Method" id="5">1</string>
</xml>

