<?xml version="1.0" encoding="UTF-8"?>
<!--This file was created by G+Smo 21.12.0-->
<xml>
 <Matrix rows="5" cols="8" id="0">0.25 55 0.2539115683853662 4.71743483964458 93.54944586201242 1.12166857808556 nan 0.03864 
0.125 171 0.03869475982351754 1.00510872434553 33.90690968726462 0.2597492615690576 nan 0.07728 
0.0625 595 0.001074518565771151 0.06079618808521205 5.59360981293248 0.02335125031334669 nan 0.15456 
0.03125 2211 5.072002939787604e-05 0.00604639212383041 1.229242997826591 0.002888163119074311 -nan 0.30912 
0.015625 8515 2.940388267981203e-06 0.0007101392682610449 0.2969457505702477 0.000364094646660789 0 0.61824 
</Matrix>
 <string label="Label" id="1">Meshsize, dofs, l2err, h1err, h2err, iFaceErr, cond_num, (penalty)</string>
 <string label="Degree" id="2">3</string>
 <string label="Regularity" id="3">2</string>
 <string label="NumRefine" id="4">4</string>
 <string label="Method" id="5">1</string>
</xml>

