<?xml version="1.0" encoding="UTF-8"?>
<!--This file was created by G+Smo 21.12.0-->
<xml>
 <Matrix rows="5" cols="8" id="0">0.25 55 0.2815525650623105 4.916401606481261 96.74884840803034 0.05006755601265115 nan 36265.04 
0.125 171 0.06568969391171061 1.443070837303905 41.342897691422 0.03621272161492789 nan 72530.08 
0.0625 595 0.001381447300363597 0.06389111802699277 5.617292871928868 0.00554468487322372 nan 145060.16 
0.03125 2211 5.149598645928187e-05 0.006047176107603838 1.228409306361298 0.0002331045652259114 nan 290120.32 
0.015625 8515 2.943778426445437e-06 0.0007099219066081288 0.2968258025667935 1.273291231735967e-05 0 580240.64 
</Matrix>
 <string label="Label" id="1">Meshsize, dofs, l2err, h1err, h2err, iFaceErr, cond_num, (penalty)</string>
 <string label="Degree" id="2">3</string>
 <string label="Regularity" id="3">2</string>
 <string label="NumRefine" id="4">4</string>
 <string label="Method" id="5">1</string>
</xml>

