<?xml version="1.0" encoding="UTF-8"?>
<!--This file was created by G+Smo 21.12.0-->
<xml>
 <Matrix rows="5" cols="8" id="0">0.25 55 0.2539590678831249 4.718902473352385 93.61052424714091 1.2458593135582 nan 1.78716 
0.125 171 0.03870600306402581 1.005304384860444 33.91397580737152 0.2714924704204882 nan 3.57432 
0.0625 595 0.0010746469537082 0.06080459956466472 5.59515508189345 0.02581374437673233 nan 7.14864 
0.03125 2211 5.07239510236649e-05 0.006047004669483978 1.229464933491004 0.0032110849741075 nan 14.29728 
0.015625 8515 2.940514093885383e-06 0.0007101797499550772 0.2969748226226224 0.0004051069832489094 0 28.59456 
</Matrix>
 <string label="Label" id="1">Meshsize, dofs, l2err, h1err, h2err, iFaceErr, cond_num, (penalty)</string>
 <string label="Degree" id="2">3</string>
 <string label="Regularity" id="3">2</string>
 <string label="NumRefine" id="4">4</string>
 <string label="Method" id="5">1</string>
</xml>

