<?xml version="1.0" encoding="UTF-8"?>
<!--This file was created by G+Smo 21.12.0-->
<xml>
 <Matrix rows="5" cols="8" id="0">0.25 55 0.2539112527165289 4.71742523376457 93.54906042849901 1.120836951726392 -nan 0.02548 
0.125 171 0.03869467684925134 1.005107322906657 33.90686442738919 0.259672713662777 -nan 0.05096 
0.0625 595 0.00107451769625433 0.06079613309783512 5.593599950321674 0.02333467908912033 nan 0.10192 
0.03125 2211 5.072000324277888e-05 0.006046388140404518 1.229241582517299 0.002885984245041683 nan 0.20384 
0.015625 8515 2.940387401296921e-06 0.0007101390052540176 0.2969455652521074 0.0003638178983517854 0 0.40768 
</Matrix>
 <string label="Label" id="1">Meshsize, dofs, l2err, h1err, h2err, iFaceErr, cond_num, (penalty)</string>
 <string label="Degree" id="2">3</string>
 <string label="Regularity" id="3">2</string>
 <string label="NumRefine" id="4">4</string>
 <string label="Method" id="5">1</string>
</xml>

