<?xml version="1.0" encoding="UTF-8"?>
<!--This file was created by G+Smo 21.12.0-->
<xml>
 <Matrix rows="5" cols="8" id="0">0.25 55 0.2571078908601502 4.94963613417806 115.8799030009799 10.33318990164456 -nan 18.43544 
0.125 171 0.04525961694231922 1.633682571622419 124.1758709351438 14.72390619409395 nan 36.87088 
0.0625 595 0.001113532531534735 0.06949928736701336 8.53450787921112 0.564868124981685 nan 73.74176 
0.03125 2211 6.644258805874128e-05 0.01127300978199746 3.809588487674438 0.2262731216121487 nan 147.48352 
0.015625 8515 3.235496856241573e-06 0.0009338729468932931 0.5405824845961605 0.02027873406728978 0 294.96704 
</Matrix>
 <string label="Label" id="1">Meshsize, dofs, l2err, h1err, h2err, iFaceErr, cond_num, (penalty)</string>
 <string label="Degree" id="2">3</string>
 <string label="Regularity" id="3">2</string>
 <string label="NumRefine" id="4">4</string>
 <string label="Method" id="5">1</string>
</xml>

