<?xml version="1.0" encoding="UTF-8"?>
<!--This file was created by G+Smo 21.12.0-->
<xml>
 <Matrix rows="5" cols="8" id="0">0.125 63 0.1481970983257462 3.484275577531729 132.6783397808402 0.9506262271020682 nan 18.92848 
0.0625 187 0.01111168349817223 0.4024143446855666 17.80500121857062 0.02933178514345609 -nan 37.85696 
0.03125 627 0.000297143492112995 0.02719958304138207 2.76282023470569 0.001730881047801455 nan 75.71392 
0.015625 2275 1.396387670611785e-05 0.00282468107150526 0.6334916211819356 0.0001752733745078494 nan 151.42784 
0.0078125 8643 8.021953018842621e-07 0.0003356171027201936 0.1547700304497539 2.09550256828844e-05 0 302.85568 
</Matrix>
 <string label="Label" id="1">Meshsize, dofs, l2err, h1err, h2err, iFaceErr, cond_num, (penalty)</string>
 <string label="Degree" id="2">3</string>
 <string label="Regularity" id="3">2</string>
 <string label="NumRefine" id="4">4</string>
 <string label="Method" id="5">1</string>
</xml>

